{
  "node_modules/.pnpm/@sveltejs+kit@1.0.0-next.484_svelte@3.50.1+vite@3.1.2/node_modules/@sveltejs/kit/src/runtime/client/start.js": {
    "file": "_app/immutable/start-ab3fa3e7.js",
    "src": "node_modules/.pnpm/@sveltejs+kit@1.0.0-next.484_svelte@3.50.1+vite@3.1.2/node_modules/@sveltejs/kit/src/runtime/client/start.js",
    "isEntry": true,
    "imports": [
      "_index-9e5c50dd.js",
      "_singletons-658a00e6.js"
    ],
    "dynamicImports": [
      ".svelte-kit/generated/nodes/0.js",
      ".svelte-kit/generated/nodes/1.js",
      ".svelte-kit/generated/nodes/2.js"
    ]
  },
  "node_modules/.pnpm/@sveltejs+kit@1.0.0-next.484_svelte@3.50.1+vite@3.1.2/node_modules/@sveltejs/kit/src/runtime/components/layout.svelte": {
    "file": "_app/immutable/components/layout.svelte-70c9d402.js",
    "src": "node_modules/.pnpm/@sveltejs+kit@1.0.0-next.484_svelte@3.50.1+vite@3.1.2/node_modules/@sveltejs/kit/src/runtime/components/layout.svelte",
    "isEntry": true,
    "imports": [
      "_index-9e5c50dd.js"
    ]
  },
  "node_modules/.pnpm/@sveltejs+kit@1.0.0-next.484_svelte@3.50.1+vite@3.1.2/node_modules/@sveltejs/kit/src/runtime/components/error.svelte": {
    "file": "_app/immutable/components/error.svelte-dc3ac7ce.js",
    "src": "node_modules/.pnpm/@sveltejs+kit@1.0.0-next.484_svelte@3.50.1+vite@3.1.2/node_modules/@sveltejs/kit/src/runtime/components/error.svelte",
    "isEntry": true,
    "imports": [
      "_index-9e5c50dd.js",
      "_singletons-658a00e6.js"
    ]
  },
  "src/routes/+page.svelte": {
    "file": "_app/immutable/components/pages/_page.svelte-6b3d08a1.js",
    "src": "src/routes/+page.svelte",
    "isEntry": true,
    "imports": [
      "_index-9e5c50dd.js",
      "_index-c89fc770.js"
    ],
    "css": [
      "_app/immutable/assets/_page-3cdb0d35.css"
    ]
  },
  "src/routes/+layout.ts": {
    "file": "_app/immutable/modules/pages/_layout.ts-849208c1.js",
    "src": "src/routes/+layout.ts",
    "isEntry": true,
    "imports": [
      "__layout-81c0d46d.js"
    ]
  },
  "_singletons-658a00e6.js": {
    "file": "_app/immutable/chunks/singletons-658a00e6.js",
    "imports": [
      "_index-c89fc770.js"
    ]
  },
  "_index-9e5c50dd.js": {
    "file": "_app/immutable/chunks/index-9e5c50dd.js"
  },
  "_index-c89fc770.js": {
    "file": "_app/immutable/chunks/index-c89fc770.js",
    "imports": [
      "_index-9e5c50dd.js"
    ]
  },
  "__layout-81c0d46d.js": {
    "file": "_app/immutable/chunks/_layout-81c0d46d.js"
  },
  ".svelte-kit/generated/nodes/0.js": {
    "file": "_app/immutable/chunks/0-8d370593.js",
    "src": ".svelte-kit/generated/nodes/0.js",
    "isDynamicEntry": true,
    "imports": [
      "__layout-81c0d46d.js",
      "node_modules/.pnpm/@sveltejs+kit@1.0.0-next.484_svelte@3.50.1+vite@3.1.2/node_modules/@sveltejs/kit/src/runtime/components/layout.svelte"
    ]
  },
  ".svelte-kit/generated/nodes/1.js": {
    "file": "_app/immutable/chunks/1-18b938bd.js",
    "src": ".svelte-kit/generated/nodes/1.js",
    "isDynamicEntry": true,
    "imports": [
      "node_modules/.pnpm/@sveltejs+kit@1.0.0-next.484_svelte@3.50.1+vite@3.1.2/node_modules/@sveltejs/kit/src/runtime/components/error.svelte"
    ]
  },
  ".svelte-kit/generated/nodes/2.js": {
    "file": "_app/immutable/chunks/2-753b7211.js",
    "src": ".svelte-kit/generated/nodes/2.js",
    "isDynamicEntry": true,
    "imports": [
      "src/routes/+page.svelte"
    ]
  },
  "src/routes/+page.css": {
    "file": "_app/immutable/assets/_page-3cdb0d35.css",
    "src": "src/routes/+page.css"
  }
}